opteryx/__init__.py
opteryx/__main__.py
opteryx/__version__.py
opteryx/command.py
opteryx/compute.cpython-313-x86_64-linux-gnu.so
opteryx/config.py
opteryx/debugging.py
opteryx/exceptions.py
opteryx/query_session.py
opteryx/compiled/__init__.py
opteryx/compiled/simd_probe.cpp
opteryx/compiled/simd_probe.cpython-313-x86_64-linux-gnu.so
opteryx/compiled/simd_probe.pyx
opteryx/compiled/simd_strings.cpython-313-x86_64-linux-gnu.so
opteryx/compiled/aggregations/__init__.py
opteryx/compiled/aggregations/count_distinct.cpp
opteryx/compiled/aggregations/count_distinct.cpython-313-x86_64-linux-gnu.so
opteryx/compiled/aggregations/count_distinct.pyi
opteryx/compiled/aggregations/count_distinct.pyx
opteryx/compiled/aggregations/group_by_draken.py
opteryx/compiled/aggregations/group_by_draken.pyx
opteryx/compiled/functions/__init__.py
opteryx/compiled/functions/strings.cpp
opteryx/compiled/functions/strings.cpython-313-x86_64-linux-gnu.so
opteryx/compiled/functions/strings.pyx
opteryx/compiled/functions/timestamp.c
opteryx/compiled/functions/timestamp.cpython-313-x86_64-linux-gnu.so
opteryx/compiled/functions/timestamp.pyx
opteryx/compiled/functions/vectors.cpp
opteryx/compiled/functions/vectors.cpython-313-x86_64-linux-gnu.so
opteryx/compiled/functions/vectors.pyx
opteryx/compiled/io/__init__.py
opteryx/compiled/io/disk_reader.cpp
opteryx/compiled/io/disk_reader.cpython-313-x86_64-linux-gnu.so
opteryx/compiled/io/disk_reader.pyx
opteryx/compiled/joins/__init__.py
opteryx/compiled/joins/cross_join.pyx
opteryx/compiled/joins/filter_join.pyx
opteryx/compiled/joins/inner_join.pyx
opteryx/compiled/joins/join_definitions.cpython-313-x86_64-linux-gnu.so
opteryx/compiled/joins/joins.cpp
opteryx/compiled/joins/joins.pyx
opteryx/compiled/joins/nested_loop_join_equals.pyx
opteryx/compiled/joins/nested_loop_join_non_eqi.pyx
opteryx/compiled/joins/outer_join.pyx
opteryx/compiled/list_ops/__init__.py
opteryx_core-0.6.8.dist-info/METADATA
opteryx_core-0.6.8.dist-info/WHEEL
opteryx_core-0.6.8.dist-info/top_level.txt
opteryx_core-0.6.8.dist-info/RECORD
opteryx_core-0.6.8.dist-info/licenses/LICENSE
opteryx_core-0.6.8.dist-info/sboms/auditwheel.cdx.json
