Metadata-Version: 2.4
Name: opteryx_core
Version: 0.6.8
Summary: Opteryx Query Engine
Home-page: https://github.com/mabel-dev/opteryx/
Author-email: Justin Joyce <justin.joyce@joocer.com>
Maintainer-email: Justin Joyce <justin.joyce@joocer.com>
Project-URL: Homepage, https://opteryx.dev/
Project-URL: Documentation, https://opteryx.dev/
Project-URL: Repository, https://github.com/mabel-dev/opteryx.git
Requires-Python: >=3.13
License-File: LICENSE
Requires-Dist: aiohttp==3.13.3
Requires-Dist: numpy==2.4.1
Requires-Dist: orjson==3.11.5
Requires-Dist: orso==0.0.226
Requires-Dist: psutil==7.2.1
Requires-Dist: pyarrow==23.0.0
Requires-Dist: requests==2.32.5
Provides-Extra: testing
Requires-Dist: freezegun; extra == "testing"
Dynamic: home-page
Dynamic: license-file
Dynamic: requires-python
